LICENSE
README.md
setup.py
pynocaptcha/__init__.py
pynocaptcha.egg-info/PKG-INFO
pynocaptcha.egg-info/SOURCES.txt
pynocaptcha.egg-info/dependency_links.txt
pynocaptcha.egg-info/not-zip-safe
pynocaptcha.egg-info/requires.txt
pynocaptcha.egg-info/top_level.txt
pynocaptcha/crackers/akamai.py
pynocaptcha/crackers/aws.py
pynocaptcha/crackers/base.py
pynocaptcha/crackers/cloudflare.py
pynocaptcha/crackers/datadome.py
pynocaptcha/crackers/discord.py
pynocaptcha/crackers/hcaptcha.py
pynocaptcha/crackers/incapsula.py
pynocaptcha/crackers/kasada.py
pynocaptcha/crackers/perimeterx.py
pynocaptcha/crackers/recaptcha.py
pynocaptcha/crackers/shape.py
pynocaptcha/crackers/tls.py
pynocaptcha/crackers/unlocker.py
pynocaptcha/magneto/1.py
pynocaptcha/magneto/__init__.py
pynocaptcha/magneto/cookies.py
pynocaptcha/magneto/headers.py
pynocaptcha/magneto/response.py
pynocaptcha/magneto/session.py