Metadata-Version: 2.1
Name: pynocaptcha
Version: 3.0.6
Summary: nocaptcha.io api
License: MIT
Keywords: nocaptcha
Platform: all
Classifier: Development Status :: 5 - Production/Stable
Classifier: Intended Audience :: Developers
Classifier: License :: OSI Approved :: ISC License (ISCL)
Classifier: Natural Language :: English
Classifier: Programming Language :: Python :: 2
Classifier: Programming Language :: Python :: 2.7
Classifier: Programming Language :: Python :: 3
License-File: LICENSE
Requires-Dist: curl_cffi
Requires-Dist: loguru
Requires-Dist: rnet
